jwave/__init__.py
jwave/acoustics/__init__.py
jwave/acoustics/conversion.py
jwave/acoustics/operators.py
jwave/acoustics/pml.py
jwave/acoustics/spectral.py
jwave/acoustics/time_harmonic.py
jwave/acoustics/time_varying.py
jwave/extras/__init__.py
jwave/extras/export.py
jwave/geometry.py
jwave/logger.py
jwave/phantoms.py
jwave/signal_processing.py
jwave/utils.py
jwave-0.2.1.dist-info/LICENSE
jwave-0.2.1.dist-info/METADATA
jwave-0.2.1.dist-info/WHEEL
jwave-0.2.1.dist-info/RECORD
