Metadata-Version: 2.1
Name: jwave
Version: 0.2.1
Summary: Fast and differentiable acoustic simulations in JAX.
License: LGPL-3.0-only
Keywords: jax,acoustics,simulation,ultrasound,differentiable-programming
Author: Antonio Stanziola
Author-email: a.stanziola@ucl.ac.uk
Requires-Python: >=3.9,<4.0
Classifier: Environment :: GPU
Classifier: Environment :: GPU :: NVIDIA CUDA
Classifier: Environment :: GPU :: NVIDIA CUDA :: 11.6
Classifier: Environment :: GPU :: NVIDIA CUDA :: 11.7
Classifier: Environment :: GPU :: NVIDIA CUDA :: 11.8
Classifier: Environment :: GPU :: NVIDIA CUDA :: 12 :: 12.0
Classifier: Environment :: GPU :: NVIDIA CUDA :: 12 :: 12.1
Classifier: Intended Audience :: Education
Classifier: Intended Audience :: Science/Research
Classifier: License :: OSI Approved :: GNU Lesser General Public License v3 (LGPLv3)
Classifier: Programming Language :: Python :: 3
Classifier: Programming Language :: Python :: 3.9
Classifier: Programming Language :: Python :: 3.10
Classifier: Programming Language :: Python :: 3.11
Classifier: Programming Language :: Python :: 3.12
Classifier: Programming Language :: Python :: 3.8
Classifier: Topic :: Scientific/Engineering
Classifier: Topic :: Scientific/Engineering :: Artificial Intelligence
Classifier: Topic :: Scientific/Engineering :: Physics
Classifier: Topic :: Software Development
Classifier: Topic :: Software Development :: Libraries
Classifier: Topic :: Software Development :: Libraries :: Python Modules
Requires-Dist: jaxdf (>=0.2.8,<0.3.0)
Requires-Dist: matplotlib (>=3.0.0,<4.0.0)
Project-URL: Bug Tracker, https://github.com/ucl-bug/jwave/issues
Project-URL: Homepage, https://ucl-bug.github.io/jwave/
Project-URL: Repository, https://github.com/ucl-bug/jwave
Project-URL: Support, https://discord.gg/VtUb4fFznt
